dismantle/__init__.py
dismantle/__version__.py
dismantle/cli.py
dismantle/extension/__init__.py
dismantle/extension/extensions.py
dismantle/extension/iextension.py
dismantle/index/__init__.py
dismantle/index/_handlers.py
dismantle/package/__init__.py
dismantle/package/_formats.py
dismantle/package/_handlers.py
dismantle/plugin/__init__.py
dismantle/plugin/iplugin.py
dismantle/plugin/plugin.py
dismantle/plugin/plugins.py
dismantle/plugin/register.py
dismantle-1.1.0.dist-info/entry_points.txt
dismantle-1.1.0.dist-info/WHEEL
dismantle-1.1.0.dist-info/METADATA
dismantle-1.1.0.dist-info/licenses/LICENSE
dismantle-1.1.0.dist-info/RECORD
