Metadata-Version: 2.1
Name: dismantle
Version: 1.1.0
Summary: A module for Python to provide the ability to extend programs using packages, plugins, and extensions.
Keywords: packaging,dependency,extension,plugin,module,version
Author-email: Area28 Technologies <dev@area28.io>
Requires-Python: >=3.7
Classifier: Intended Audience :: Developers
Classifier: License :: OSI Approved :: MIT License
Classifier: Natural Language :: English
Classifier: Operating System :: OS Independent
Classifier: Programming Language :: Python :: 3
Classifier: Programming Language :: Python :: 3.10
Classifier: Programming Language :: Python :: 3.6
Classifier: Programming Language :: Python :: 3.7
Classifier: Programming Language :: Python :: 3.8
Classifier: Programming Language :: Python :: 3.9
Requires-Dist: requests>=2.28.1
Project-URL: changelog, https://github.com/area28technologies/dismantle/blob/main/CHANGELOG.md
Project-URL: documentation, https://area28technologies.github.io/dismantle/index.html
Project-URL: homepage, https://area28technologies.github.io/dismantle/index.html
Project-URL: repository, https://github.com/area28technologies/dismantle
